caspy3/__init__.py
caspy3/__main__.py
caspy3/cli.py
caspy3/qt_gui.py
caspy3/__pycache__/__init__.cpython-37.pyc
caspy3/__pycache__/__init__.cpython-38.pyc
caspy3/__pycache__/__main__.cpython-38.pyc
caspy3/__pycache__/cli.cpython-37.pyc
caspy3/__pycache__/cli.cpython-38.pyc
caspy3/__pycache__/qt_gui.cpython-37.pyc
caspy3/__pycache__/qt_gui.cpython-38.pyc
caspy3/assets/__init__.py
caspy3/assets/logo.ico
caspy3/assets/logo.png
caspy3/assets/icons/16x16.png
caspy3/assets/icons/24x24.png
caspy3/assets/icons/256x256.png
caspy3/assets/icons/32x32.png
caspy3/assets/icons/48x48.png
caspy3/assets/icons/64x64.png
caspy3/assets/icons/923x914.png
caspy3/data/__init__.py
caspy3/data/formulas.json
caspy3/data/settings.json
caspy3/data/websites.json
caspy3/qt_assets/__init__.py
caspy3/qt_assets/drag_label.py
caspy3/qt_assets/highlight.py
caspy3/qt_assets/latex.py
caspy3/qt_assets/main.py
caspy3/qt_assets/main.ui
caspy3/qt_assets/pixmap_viewer.py
caspy3/qt_assets/__pycache__/__init__.cpython-38.pyc
caspy3/qt_assets/__pycache__/drag_label.cpython-38.pyc
caspy3/qt_assets/__pycache__/highlight.cpython-38.pyc
caspy3/qt_assets/__pycache__/latex.cpython-38.pyc
caspy3/qt_assets/__pycache__/main.cpython-37.pyc
caspy3/qt_assets/__pycache__/main.cpython-38.pyc
caspy3/qt_assets/__pycache__/pixmap_viewer.cpython-38.pyc
caspy3/qt_assets/dialogs/__init__.py
caspy3/qt_assets/dialogs/dialog_add_website.py
caspy3/qt_assets/dialogs/dialog_remove_website.py
caspy3/qt_assets/dialogs/dialog_view.py
caspy3/qt_assets/dialogs/dialog_view_text.py
caspy3/qt_assets/dialogs/main_view_a.ui
caspy3/qt_assets/dialogs/main_view_e.ui
caspy3/qt_assets/dialogs/save_dialog.ui
caspy3/qt_assets/dialogs/tab_list.py
caspy3/qt_assets/dialogs/tab_list.ui
caspy3/qt_assets/dialogs/web_add.ui
caspy3/qt_assets/dialogs/web_remove.ui
caspy3/qt_assets/dialogs/__pycache__/__init__.cpython-37.pyc
caspy3/qt_assets/dialogs/__pycache__/__init__.cpython-38.pyc
caspy3/qt_assets/dialogs/__pycache__/dialog_add_website.cpython-37.pyc
CASPy3-2.2.0.dist-info/LICENSE
CASPy3-2.2.0.dist-info/METADATA
CASPy3-2.2.0.dist-info/WHEEL
CASPy3-2.2.0.dist-info/entry_points.txt
CASPy3-2.2.0.dist-info/top_level.txt
CASPy3-2.2.0.dist-info/RECORD
