Metadata-Version: 2.1
Name: CASPy3
Version: 2.2.0
Summary: A program that provides both a GUI and a CLI to SymPy, a symbolic computation and computer algebra system Python library.
Home-page: https://github.com/Secozzi/CASPy
Author: Folke Ishii
Author-email: folke.ishii@gmail.com
License: GPLv3+
Platform: UNKNOWN
Classifier: License :: OSI Approved :: GNU General Public License v3 or later (GPLv3+)
Classifier: Topic :: Scientific/Engineering :: Mathematics
Classifier: Programming Language :: Python :: 3
Classifier: Programming Language :: Python :: 3.8
Classifier: Programming Language :: Python :: 3 :: Only
Requires-Python: >=3.8
Requires-Dist: PyQt5 (>=5.15.0)
Requires-Dist: PyQtWebEngine (>=5.15.0)
Requires-Dist: sympy (>=1.6.1)
Requires-Dist: pyperclip (>=1.7.0)
Requires-Dist: click (>=7.1.1)
Requires-Dist: colored (>=1.4.2)
Requires-Dist: qtconsole (>=5.0.0)
